[
  {
    "Sl": 1401,
    "customerName": "Stec",
    "accountName": "stecacc",
    "unitName": "stecunit",
    "servicelocation": "Trivandrum",
    "business": "AMC",
    "ponumber": "PL:12:AMC:10:2016-17/2675",
    "podate": "10/30/19",
    "producttype": "Switch",
    "brand": "D-Link",
    "model": "8 Port Switch",
    "serialno": "QBTJ1D2000197",
    "contractfrom": "10/23/19",
    "contractto": "10/22/22",
    "billingfrom": "10/23/19",
    "billingto": "10/22/22",
    "amcrate": 1500,
    "GST%": "18%",
    "gstperc": 18,
    "gstamount": 270,
    "netamount": 1770,
    "os": "",
    "CPU Qty": "",
    "cpu1": "theone",
    "cpu1sno": "1234",
    "cpu2": "thetwo",
    "cpu2sno": "3510",
    "cpu3": "thethree",
    "cpu3sno": "2410",
    "cpu4": "",
    "cpu4sno": "",
    "RAM Qty": "",
    "ram1": "",
    "ram1sno": "",
    "ram2": "",
    "ram2sno": "",
    "ram3": "",
    "ram3sno": "",
    "ram4": "",
    "ram4sno": "",
    "HDD Qty": "",
    "hdd1": "",
    "hdd1sno": "",
    "hdd2": "",
    "hdd2sno": "",
    "hdd3": "",
    "hdd3sno": "",
    "hdd4": "",
    "hdd4sno": "",
    "SMPS Qty": "",
    "smps1": "",
    "smps1sno": "",
    "smps2": "",
    "smps2sno": "",
    "smps3": "",
    "smps3sno": "",
    "smps4": "",
    "smps4sno": "",
    "CPU FAN Qty": "",
    "fan1": "",
    "fan1sno": "",
    "fan2": "",
    "fan2sno": "",
    "fan3": "",
    "fan3sno": "",
    "fan4": "",
    "fan4sno": "",
    "motherboard1": "",
    "motherboard1sno": "",
    "opticaldrive1": "",
    "opticaldrive1sno": "",
    "kbd1": "",
    "kbd1sno": "",
    "mouse1": "",
    "mouse1sno": "",
    "monitor1": "",
    "monitor1sno": "",
    "gcard1": "",
    "gcard1sno": "",
    "enetcard1": "",
    "enetcard1sno": "",
    "others1": "",
    "others1sno": "",
    "serialcard1": "",
    "serialcard1sno": "",
    "paralellcard1": "",
    "paralellcard1sno": "",
    "HBA Card": "",
    "HBA Sl No": "",
    "Raid Controller": "",
    "Raid Sl No": "",
    "Tape Drive": "",
    "Tape Sl No": "",
    "tapecontroller1": "",
    "tapecontroller1sno": "",
    "raidcontroller1": "",
    "raidcontroller1sno": "",
    "hbacard1": "",
    "hbacard1sno": ""
  }
]
